autotsf/__init__.py
autotsf/data_preprocessing/__init__.py
autotsf/data_preprocessing/calenderTrans.py
autotsf/data_preprocessing/categorical_features.py
autotsf/data_preprocessing/feature_engineering.py
autotsf/data_preprocessing/salesHistoryTrans.py
autotsf/data_preprocessing/seasonality_test.py
autotsf/data_preprocessing/trend_test.py
autotsf/flows/__init__.py
autotsf/flows/auto_tsf.py
autotsf/flows/autotsf.py
autotsf/flows/data_collection.py
autotsf/flows/data_processing_and_transform.py
autotsf/flows/model_training.py
autotsf/flows/tests/__init__.py
autotsf/flows/tests/test_autotsf.py
autotsf/flows/tests/test_data_processing_and_transform.py
autotsf/flows/tests/test_model_training.py
autotsf/models/__init__.py
autotsf/models/generalized_linear_model.py
autotsf/models/lgbm.py
autotsf/models/lstm.py
autotsf/models/models.py
autotsf/models/stacked_model.py
autotsf/utils/__init__.py
autotsf/utils/_testing.py
autotsf/utils/import_modules.py
autotsf/utils/time_series_utils.py
Autotsf-0.0.8.dist-info/LICENSE
Autotsf-0.0.8.dist-info/METADATA
Autotsf-0.0.8.dist-info/WHEEL
Autotsf-0.0.8.dist-info/top_level.txt
Autotsf-0.0.8.dist-info/RECORD
