Metadata-Version: 2.1
Name: Autotsf
Version: 0.0.8
Summary: Automated Time-Series Forecasting
Home-page: https://github.com/kailingding/Autotsf
Author: Kailing Ding
Author-email: markdingkl@gmail.com
License: MIT
Platform: UNKNOWN
Classifier: License :: OSI Approved :: MIT License
Classifier: Programming Language :: Python :: 3
Classifier: Programming Language :: Python :: 3.6
Requires-Dist: pandas (==1.0.3)
Requires-Dist: numpy (==1.18.2)
Requires-Dist: scikit-learn (==0.22.2.post1)
Requires-Dist: hyperopt (==0.2.2)
Requires-Dist: keras (==2.3.0)
